targeting_workflow/__init__.py
targeting_workflow/database/__init__.py
targeting_workflow/database/database.py
targeting_workflow/database/database_plots.py
targeting_workflow/database/database_utils.py
targeting_workflow/database/export.py
targeting_workflow/features/__init__.py
targeting_workflow/features/base_feature.py
targeting_workflow/features/dbscan.py
targeting_workflow/features/kmean.py
targeting_workflow/features/knowledge_feature.py
targeting_workflow/features/pca.py
targeting_workflow/gui/__init__.py
targeting_workflow/gui/auto_generated/__init__.py
targeting_workflow/gui/auto_generated/qt_gui.py
targeting_workflow/gui/config.py
targeting_workflow/gui/main_window.py
targeting_workflow/gui/tab_modelling.py
targeting_workflow/gui/tab_property_eda.py
targeting_workflow/gui/tab_property_selection.py
targeting_workflow/gui/tab_train_test.py
targeting_workflow/gui/threads.py
targeting_workflow/predictors/__init__.py
targeting_workflow/predictors/base_predictor.py
targeting_workflow/predictors/gaussian_nb.py
targeting_workflow/predictors/knowledge_predictor.py
targeting_workflow/predictors/random_forest.py
targeting_workflow/shared/__init__.py
targeting_workflow/shared/base_compute.py
targeting_workflow/shared/geoh5py_utils.py
targeting_workflow/shared/knowledge_driven.py
targeting_workflow/shared/plots.py
targeting_workflow/shared/utils.py
targeting_workflow-assets/__init__.py
targeting_workflow-assets/icon/download.png
targeting_workflow-assets/icon/prism-ball-10cm.png
targeting_workflow-assets/MPM_input.geoh5
targeting_workflow-assets/plotly/plotly-2.18.0.min.js
targeting_workflow-assets/qt_gui.ui
targeting_workflow-assets/uijson/targeting_workflow.ui.json
targeting_workflow-0.1.0a1.dist-info/entry_points.txt
targeting_workflow-0.1.0a1.dist-info/METADATA
targeting_workflow-0.1.0a1.dist-info/WHEEL
targeting_workflow-0.1.0a1.dist-info/RECORD
